VertexEngine/VertexWebEngineCore/JSBridge.py
VertexEngine/VertexWebEngineCore/WebEngineURLInterceptor.py
VertexEngine/VertexWebEngineCore/WebPage.py
VertexEngine/VertexWebEngineCore/WebProfile.py
VertexEngine/VertexWebEngineCore/WebScene.py
VertexEngine/VertexWebEngineWidgets/EngineView.py
VertexEngine/WebBrowserSystem/BrowserToolBar.py
VertexEngine/WebBrowserSystem/downloads.py
vertexengine_webengine-1.2rc3.dist-info/licenses/LICENSE
vertexengine_webengine-1.2rc3.dist-info/METADATA
vertexengine_webengine-1.2rc3.dist-info/WHEEL
vertexengine_webengine-1.2rc3.dist-info/top_level.txt
vertexengine_webengine-1.2rc3.dist-info/RECORD
