Metadata-Version: 2.4
Name: VertexEngine-WebEngine
Version: 1.2rc3
Summary: The offical WebEngine Extension of the VertexEngine SDK.
Author-email: Tyrel Miguel <annbasilan0828@gmail.com>
License: MIT
Project-URL: Documentation, https://vertexenginedocs.netlify.app/
Project-URL: Homepage, https://github.com/TyrelGomez/VertexEngine-WebEngine-Code
Requires-Python: >=3.10
License-File: LICENSE
Requires-Dist: pygame>=2.0
Requires-Dist: PyQt6>=6.7
Requires-Dist: VertexEngine>=1.0.1
Requires-Dist: PyQt6-WebEngine>=6.3.0
Dynamic: license-file
